Metadata-Version: 2.4
Name: adafruit-circuitpython-fingerprint
Version: 2.2.23
Summary: CircuitPython library for UART fingerprint sensor.
Author-email: Adafruit Industries <circuitpython@adafruit.com>
License: MIT
Project-URL: Homepage, https://github.com/adafruit/Adafruit_CircuitPython_Fingerprint
Keywords: adafruit,uart,fingerprint,finger,print,sensor,hardware,micropython,circuitpython
Classifier: Intended Audience :: Developers
Classifier: Topic :: Software Development :: Libraries
Classifier: Topic :: Software Development :: Embedded Systems
Classifier: Topic :: System :: Hardware
Classifier: License :: OSI Approved :: MIT License
Classifier: Programming Language :: Python :: 3
License-File: LICENSE
Requires-Dist: Adafruit-Blinka
Requires-Dist: pyserial
Provides-Extra: optional
Requires-Dist: numpy; extra == "optional"
Requires-Dist: matplotlib; extra == "optional"
Requires-Dist: pyserial; extra == "optional"
Dynamic: license-file
